easy_chromium_controller/__init__.py
easy_chromium_controller/core.py
easy_chromium_controller/utils.py
easy_chromium_controller-1.0.9.dist-info/LICENSE
easy_chromium_controller-1.0.9.dist-info/METADATA
easy_chromium_controller-1.0.9.dist-info/WHEEL
easy_chromium_controller-1.0.9.dist-info/top_level.txt
easy_chromium_controller-1.0.9.dist-info/RECORD
