Metadata-Version: 2.1
Name: easy-chromium-controller
Version: 1.0.9
License-File: LICENSE
Requires-Dist: selenium (==4.12.0)
Requires-Dist: Pillow (==10.0.0)
Requires-Dist: psutil (==5.9.5)
Requires-Dist: wget (==3.2)
Requires-Dist: regex (==2023.8.8)
